{
  "Q181018": "hu.bacs_kiskun",
  "Q186195": "hu.baranya",
  "Q191616": "hu.bekes",
  "Q188895": "hu.borsod_abauj_zemplen",
  "Q193031": "hu.csongrad",
  "Q187693": "hu.fejer",
  "Q187753": "hu.gyor_moson_sopron",
  "Q185368": "hu.hajdu_bihar",
  "Q191604": "hu.heves",
  "Q189655": "hu.jasz_nagykun_szolnok",
  "Q190018": "hu.komarom_esztergom",
  "Q194273": "hu.nograd",
  "Q188612": "hu.pest",
  "Q190522": "hu.somogy",
  "Q190518": "hu.szabolcs_szatmar_bereg",
  "Q191625": "hu.tolna",
  "Q187677": "hu.vas",
  "Q188890": "hu.veszprem",
  "Q185374": "hu.zala",
  "Q1781": "hu.budapest"
}
